MANIFEST.in
README
build_exe.py
setup.py
squeezeui-controller.py
squeezeui-player.py
bin/squeezeui
bin/squeezeui-controller-exe.py
bin/squeezeui-player-exe.py
squeezeui/__init__.py
squeezeui/player.py
squeezeui.egg-info/PKG-INFO
squeezeui.egg-info/SOURCES.txt
squeezeui.egg-info/dependency_links.txt
squeezeui.egg-info/top_level.txt
squeezeui/controllers/__init__.py
squeezeui/controllers/config.py
squeezeui/controllers/mainwindow.py
squeezeui/controllers/protocol.py
squeezeui/controllers/tools.py
squeezeui/models/__init__.py
squeezeui/models/listmodel.py
squeezeui/views/App.png
squeezeui/views/App.svg
squeezeui/views/player.qml
squeezeui/views/player/ContentBlock.qml
squeezeui/views/player/ContentList.qml
squeezeui/views/player/ContentListControlButtons.qml
squeezeui/views/player/ContentListSearchBox.qml
squeezeui/views/player/CtrlButton.qml
squeezeui/views/player/Popup.qml
squeezeui/views/player/Slider.qml