Metadata-Version: 1.1
Name: squeezeui
Version: 1.0.0
Summary: Graphical user interface for Squeezebox players.
Home-page: https://bitbucket.org/fholmer/squeezeui
Author: Frode Holmer
Author-email: fholmer@gmail.com
License: GPLv3
Keywords: Squeezebox Squeezelite
Platform: UNKNOWN
Classifier: Development Status :: 4 - Beta
Classifier: Environment :: X11 Applications :: Qt
Classifier: Intended Audience :: End Users/Desktop
Classifier: License :: OSI Approved :: GNU General Public License v3 (GPLv3)
Classifier: Operating System :: POSIX :: Linux
Classifier: Programming Language :: Python :: 3
Classifier: Programming Language :: Python :: 3.3
Classifier: Topic :: Multimedia :: Sound/Audio
Classifier: Topic :: Multimedia :: Sound/Audio :: Players
Requires: PySide (>=1.1.2)
Requires: jsonrpclib (>=0.1.6)
Provides: squeezeui (1.0.0)
